setup.py
emppub/__init__.py
emppub.egg-info/PKG-INFO
emppub.egg-info/SOURCES.txt
emppub.egg-info/dependency_links.txt
emppub.egg-info/top_level.txt